Mapproxy112ZhongwenWendang/README.md
Mapproxy112ZhongwenWendang/__init__.py
Mapproxy112ZhongwenWendang/__main__.py
Mapproxy112ZhongwenWendang/file.epub
Mapproxy112ZhongwenWendang/index.html
Mapproxy112ZhongwenWendang/css/__init__.py
Mapproxy112ZhongwenWendang/css/annotations.css
Mapproxy112ZhongwenWendang/css/main.css
Mapproxy112ZhongwenWendang/css/normalize.css
Mapproxy112ZhongwenWendang/css/popup.css
Mapproxy112ZhongwenWendang/font/__init__.py
Mapproxy112ZhongwenWendang/font/fontello.eot
Mapproxy112ZhongwenWendang/font/fontello.svg
Mapproxy112ZhongwenWendang/font/fontello.ttf
Mapproxy112ZhongwenWendang/font/fontello.woff
Mapproxy112ZhongwenWendang/img/__init__.py
Mapproxy112ZhongwenWendang/img/annotator-glyph-sprite.png
Mapproxy112ZhongwenWendang/img/annotator-icon-sprite.png
Mapproxy112ZhongwenWendang/img/apple-touch-icon.png
Mapproxy112ZhongwenWendang/img/cancelfullscreen.png
Mapproxy112ZhongwenWendang/img/close.png
Mapproxy112ZhongwenWendang/img/fullscreen.png
Mapproxy112ZhongwenWendang/img/loader.gif
Mapproxy112ZhongwenWendang/img/menu-icon.png
Mapproxy112ZhongwenWendang/img/save.png
Mapproxy112ZhongwenWendang/img/saved.png
Mapproxy112ZhongwenWendang/img/settings-s.png
Mapproxy112ZhongwenWendang/img/settings.png
Mapproxy112ZhongwenWendang/img/star.png
Mapproxy112ZhongwenWendang/js/__init__.py
Mapproxy112ZhongwenWendang/js/epub.js
Mapproxy112ZhongwenWendang/js/epub.min.js
Mapproxy112ZhongwenWendang/js/epub.min.map
Mapproxy112ZhongwenWendang/js/hooks.min.js
Mapproxy112ZhongwenWendang/js/hooks.min.map
Mapproxy112ZhongwenWendang/js/reader.js
Mapproxy112ZhongwenWendang/js/reader.js.map
Mapproxy112ZhongwenWendang/js/reader.min.js
Mapproxy112ZhongwenWendang/js/reader.min.map
Mapproxy112ZhongwenWendang/js/hooks/__init__.py
Mapproxy112ZhongwenWendang/js/hooks/extensions/__init__.py
Mapproxy112ZhongwenWendang/js/hooks/extensions/highlight.js
Mapproxy112ZhongwenWendang/js/libs/__init__.py
Mapproxy112ZhongwenWendang/js/libs/jquery.min.js
mapproxy_1_12_zhongwen_wendang-2024.3.5.0.dist-info/METADATA
mapproxy_1_12_zhongwen_wendang-2024.3.5.0.dist-info/WHEEL
mapproxy_1_12_zhongwen_wendang-2024.3.5.0.dist-info/entry_points.txt
mapproxy_1_12_zhongwen_wendang-2024.3.5.0.dist-info/top_level.txt
mapproxy_1_12_zhongwen_wendang-2024.3.5.0.dist-info/RECORD
